{
  "project_info": {
    "project_number": "611775071009",
    "project_id": "kv-app-db6ba",
    "storage_bucket": "kv-app-db6ba.firebasestorage.app"
  },
  "client": [
    {
      "client_info": {
        "mobilesdk_app_id": "1:611775071009:android:4010a7ad26a32e25747460",
        "android_client_info": {
          "package_name": "com.example.kisanverse"
        }
      },
      "oauth_client": [],
      "api_key": [
        {
          "current_key": "AIzaSyAcSam3W8wTzWJ07xtc1wJOsz6bSE5YpA8"
        }
      ],
      "services": {
        "appinvite_service": {
          "other_platform_oauth_client": []
        }
      }
    }
  ],
  "configuration_version": "1"
}